pyanylist/__init__.py
pyanylist/client.py
pyanylist/credentials.py
pyanylist/errors.py
pyanylist/messages_pb2.py
pyanylist/messages_pb2.pyi
pyanylist/model.py
anylist-0.0.1rc1.dist-info/METADATA
anylist-0.0.1rc1.dist-info/WHEEL
anylist-0.0.1rc1.dist-info/top_level.txt
anylist-0.0.1rc1.dist-info/RECORD
